[{"entities":[{"evidence":4,"title":" @rrhoover","is_about":true,"confident":true,"entity_type":"Person","sentiment_score":0.0,"sentiment_polarity":"neutral","label":"Twitterer","type":"named"},{"evidence":4,"title":" @ProductHunt","is_about":true,"confident":true,"entity_type":"Person","sentiment_score":0.0,"sentiment_polarity":"neutral","label":"Twitterer","type":"named"},{"evidence":0,"title":"  http://t.co/xWKOtXDoax","is_about":false,"confident":true,"entity_type":"Regex","sentiment_score":0.0,"sentiment_polarity":"neutral","label":"url","type":"named"},{"evidence":0,"title":"  http://t.co/h1zCZcMMxu","is_about":false,"confident":true,"entity_type":"Regex","sentiment_score":0.0,"sentiment_polarity":"neutral","label":"url","type":"named"}],"status":"PROCESSED","summary":"RT  @rrhoover: Introducing the  @ProductHunt Games Digest:   http://t.co/xWKOtXDoax 👾💥 More details here:   http://t.co/h1zCZcMMxu   http://t.co/s…... ","config_id":"1d9a3af7-825a-4a64-92fa-f05fa11ba5c7","source_text":"RT @rrhoover: Introducing the @ProductHunt Games Digest: http://t.co/xWKOtXDoax 👾💥\n\nMore details here: http://t.co/h1zCZcMMxu http://t.co/s…","language_score":12.0,"sentiment_score":0.0,"sentiment_polarity":"neutral","language":"English","id":"5960206701"},{"entities":[{"evidence":7,"title":" @ow","is_about":true,"confident":true,"entity_type":"Person","sentiment_score":0.6,"sentiment_polarity":"positive","label":"Twitterer","type":"named"},{"evidence":7,"title":" @producthunt","is_about":true,"confident":true,"entity_type":"Person","sentiment_score":0.6,"sentiment_polarity":"positive","label":"Twitterer","type":"named"},{"evidence":0,"title":"  http://t.co/Twii1yyohE","is_about":false,"confident":true,"entity_type":"Regex","sentiment_score":0.0,"sentiment_polarity":"neutral","label":"url","type":"named"}],"status":"PROCESSED","phrases":[{"title":"love","sentiment_score":0.6,"sentiment_polarity":"positive","is_negated":false,"is_intensified":false,"type":"detected"}],"summary":"RT  @ow: why i love  @producthunt   http://t.co/Twii1yyohE... ","config_id":"1d9a3af7-825a-4a64-92fa-f05fa11ba5c7","source_text":"RT @ow: why i love @producthunt http://t.co/Twii1yyohE","language_score":5.0,"sentiment_score":0.6,"sentiment_polarity":"positive","language":"English","id":"8061389778"},{"entities":[{"evidence":4,"title":" @JustHistoryPics","is_about":true,"confident":true,"entity_type":"Person","sentiment_score":0.0,"sentiment_polarity":"neutral","label":"Twitterer","type":"named"},{"evidence":4,"title":"Coca-Cola","is_about":true,"confident":true,"entity_type":"Company","sentiment_score":0.0,"sentiment_polarity":"neutral","label":"Company","type":"named"},{"evidence":0,"title":"  http://t.co/S93pNw7RgJ","is_about":false,"confident":true,"entity_type":"Regex","sentiment_score":0.0,"sentiment_polarity":"neutral","label":"url","type":"named"}],"status":"PROCESSED","summary":"RT  @JustHistoryPics: Old school Coca-Cola ad   http://t.co/S93pNw7RgJ... ","config_id":"1d9a3af7-825a-4a64-92fa-f05fa11ba5c7","source_text":"RT @JustHistoryPics: Old school Coca-Cola ad http://t.co/S93pNw7RgJ","language_score":4.0,"sentiment_score":0.0,"sentiment_polarity":"neutral","topics":[{"hitcount":0,"title":"Advertising","sentiment_score":0.0,"strength_score":0.5357318,"sentiment_polarity":"neutral","type":"concept"},{"hitcount":1,"title":"Education","sentiment_score":0.0,"strength_score":0.0,"sentiment_polarity":"neutral","type":"query"}],"language":"English","id":"0727982244"},{"status":"FAILED","summary":"Failed to parse document","config_id":"1d9a3af7-825a-4a64-92fa-f05fa11ba5c7","sentiment_score":0.0,"sentiment_polarity":"neutral","id":"4149575651"},{"status":"FAILED","summary":"Failed to parse document","config_id":"1d9a3af7-825a-4a64-92fa-f05fa11ba5c7","sentiment_score":0.0,"sentiment_polarity":"neutral","id":"5953801840"},{"entities":[{"themes":[{"title":"Real programmers","stemmed":"real programmer","evidence":4,"normalized":"real programmer","is_about":false,"sentiment_score":-0.08665371,"strength_score":1.0,"sentiment_polarity":"neutral"},{"title":"invalid solution","stemmed":"invalid solution","evidence":4,"normalized":"invalid solution","is_about":false,"sentiment_score":-0.5343611,"strength_score":1.0,"sentiment_polarity":"negative"},{"title":"author posts","stemmed":"author post","evidence":4,"normalized":"author post","is_about":false,"sentiment_score":-0.08665371,"strength_score":1.0,"sentiment_polarity":"neutral"}],"evidence":7,"title":" #4","is_about":true,"confident":true,"entity_type":"Pattern","sentiment_score":-0.08665371,"sentiment_polarity":"neutral","label":"Hashtag","type":"named"},{"themes":[{"title":"Real programmers","stemmed":"real programmer","evidence":4,"normalized":"real programmer","is_about":false,"sentiment_score":-0.08665371,"strength_score":1.0,"sentiment_polarity":"neutral"},{"title":"invalid solution","stemmed":"invalid solution","evidence":4,"normalized":"invalid solution","is_about":false,"sentiment_score":-0.5343611,"strength_score":1.0,"sentiment_polarity":"negative"},{"title":"author posts","stemmed":"author post","evidence":4,"normalized":"author post","is_about":false,"sentiment_score":-0.08665371,"strength_score":1.0,"sentiment_polarity":"neutral"}],"evidence":4,"title":" @rickasaurus","is_about":true,"confident":true,"entity_type":"Person","sentiment_score":0.0,"sentiment_polarity":"neutral","label":"Twitterer","type":"named"},{"themes":[{"title":"Real programmers","stemmed":"real programmer","evidence":4,"normalized":"real programmer","is_about":false,"sentiment_score":-0.08665371,"strength_score":1.0,"sentiment_polarity":"neutral"},{"title":"invalid solution","stemmed":"invalid solution","evidence":4,"normalized":"invalid solution","is_about":false,"sentiment_score":-0.5343611,"strength_score":1.0,"sentiment_polarity":"negative"},{"title":"author posts","stemmed":"author post","evidence":4,"normalized":"author post","is_about":false,"sentiment_score":-0.08665371,"strength_score":1.0,"sentiment_polarity":"neutral"}],"evidence":4,"title":"\"Real programmers can do these problems easily\"","is_about":false,"confident":true,"entity_type":"Quote","sentiment_score":0.1372,"sentiment_polarity":"neutral","label":"Quote","type":"named"},{"themes":[{"title":"Real programmers","stemmed":"real programmer","evidence":4,"normalized":"real programmer","is_about":false,"sentiment_score":-0.08665371,"strength_score":1.0,"sentiment_polarity":"neutral"},{"title":"invalid solution","stemmed":"invalid solution","evidence":4,"normalized":"invalid solution","is_about":false,"sentiment_score":-0.5343611,"strength_score":1.0,"sentiment_polarity":"negative"},{"title":"author posts","stemmed":"author post","evidence":4,"normalized":"author post","is_about":false,"sentiment_score":-0.08665371,"strength_score":1.0,"sentiment_polarity":"neutral"}],"evidence":0,"title":"https://t.co/IDtTyJELl1","is_about":false,"confident":true,"entity_type":"Regex","sentiment_score":0.0,"sentiment_polarity":"neutral","label":"url","type":"named"}],"status":"PROCESSED","themes":[{"title":"Real programmers","stemmed":"real programmer","evidence":4,"normalized":"real programmer","is_about":true,"sentiment_score":-0.08665371,"strength_score":1.0,"sentiment_polarity":"neutral"},{"title":"invalid solution","stemmed":"invalid solution","evidence":4,"normalized":"invalid solution","is_about":true,"sentiment_score":-0.5343611,"strength_score":1.0,"sentiment_polarity":"negative"},{"title":"author posts","stemmed":"author post","evidence":4,"normalized":"author post","is_about":true,"sentiment_score":-0.08665371,"strength_score":1.0,"sentiment_polarity":"neutral"}],"phrases":[{"title":"invalid","sentiment_score":-0.5343611,"sentiment_polarity":"negative","is_negated":false,"is_intensified":false,"type":"detected"},{"title":"problems","sentiment_score":-0.49,"sentiment_polarity":"negative","is_negated":false,"is_intensified":false,"type":"detected"},{"title":"easily","sentiment_score":0.7644,"sentiment_polarity":"positive","is_negated":false,"is_intensified":false,"type":"detected"},{"title":"Real programmers","sentiment_polarity":"neutral","type":"possible"}],"summary":"RT  @rickasaurus: \"Real programmers can do these problems easily\"; author posts invalid solution to  #4 https://t.co/IDtTyJELl1... ","auto_categories":[{"title":"Chemistry","strength_score":0.5579413,"type":"node"}],"config_id":"1d9a3af7-825a-4a64-92fa-f05fa11ba5c7","source_text":"RT @rickasaurus: \"Real programmers can do these problems easily\"; author posts invalid solution to #4 https://t.co/IDtTyJELl1","language_score":9.0,"sentiment_score":-0.08665371,"sentiment_polarity":"negative","language":"English","id":"1383948261"},{"entities":[{"evidence":4,"title":" #HackFMI","is_about":true,"confident":true,"entity_type":"Pattern","sentiment_score":0.0,"sentiment_polarity":"neutral","label":"Hashtag","type":"named"},{"evidence":0,"title":"https://t.co/nqedrBoQAN","is_about":false,"confident":true,"entity_type":"Regex","sentiment_score":0.0,"sentiment_polarity":"neutral","label":"url","type":"named"}],"status":"PROCESSED","summary":" #HackFMI 5 highlights - https://t.co/nqedrBoQAN !... ","config_id":"1d9a3af7-825a-4a64-92fa-f05fa11ba5c7","source_text":"#HackFMI 5 highlights - https://t.co/nqedrBoQAN !","language_score":2.0,"sentiment_score":0.0,"sentiment_polarity":"neutral","topics":[{"hitcount":0,"title":"Sports","sentiment_score":0.0,"strength_score":0.6247493,"sentiment_polarity":"neutral","type":"concept"}],"language":"English","id":"3472331694"},{"entities":[{"evidence":6,"title":" @rob_pike","is_about":true,"confident":true,"entity_type":"Person","sentiment_score":0.4,"sentiment_polarity":"neutral","label":"Twitterer","type":"named"}],"status":"PROCESSED","phrases":[{"title":"easier","sentiment_score":0.49,"sentiment_polarity":"positive","is_negated":false,"is_intensified":false,"type":"detected"},{"title":"Rather","sentiment_score":0.4,"sentiment_polarity":"positive","is_negated":false,"is_intensified":false,"type":"detected"}],"summary":"RT  @rob_pike: Rather than teach everyone to code, let's teach them to think... The coding can come later; it's easier... ","config_id":"1d9a3af7-825a-4a64-92fa-f05fa11ba5c7","source_text":"RT @rob_pike: Rather than teach everyone to code, let's teach them to think. The coding can come later; it's easier.","language_score":15.0,"sentiment_score":0.445,"sentiment_polarity":"positive","language":"English","id":"9780663755"},{"entities":[{"evidence":2,"title":" @codeconf","is_about":true,"confident":true,"entity_type":"Person","sentiment_score":0.0,"sentiment_polarity":"neutral","label":"Twitterer","type":"named"},{"evidence":0,"title":"  http://t.co/rqvoBTXw6D","is_about":false,"confident":true,"entity_type":"Regex","sentiment_score":0.0,"sentiment_polarity":"neutral","label":"url","type":"named"}],"status":"PROCESSED","phrases":[{"title":"n't forget","sentiment_polarity":"neutral","type":"possible"}],"summary":"Don't forget the  @codeconf CFP closes on Sunday at 11:59pm PDT... We want to hear from you, submit your ideas at   http://t.co/rqvoBTXw6D... ","config_id":"1d9a3af7-825a-4a64-92fa-f05fa11ba5c7","source_text":"Don't forget the @codeconf CFP closes on Sunday at 11:59pm PDT. We want to hear from you, submit your ideas at http://t.co/rqvoBTXw6D","language_score":16.0,"sentiment_score":0.0,"sentiment_polarity":"neutral","language":"English","id":"2547147682"},{"status":"FAILED","summary":"Failed to parse document","config_id":"1d9a3af7-825a-4a64-92fa-f05fa11ba5c7","sentiment_score":0.0,"sentiment_polarity":"neutral","id":"1454043879"},{"status":"FAILED","summary":"Failed to parse document","config_id":"1d9a3af7-825a-4a64-92fa-f05fa11ba5c7","sentiment_score":0.0,"sentiment_polarity":"neutral","id":"8244792657"},{"entities":[{"themes":[{"title":"IPython notebooks","stemmed":"ipython notebook","evidence":4,"normalized":"ipython notebook","is_about":false,"sentiment_score":0.0,"strength_score":1.0,"sentiment_polarity":"neutral"}],"evidence":0,"title":"https://t.co/LvEHeykDDp","is_about":false,"confident":true,"entity_type":"Regex","sentiment_score":0.0,"sentiment_polarity":"neutral","label":"url","type":"named"}],"status":"PROCESSED","themes":[{"title":"IPython notebooks","stemmed":"ipython notebook","evidence":4,"normalized":"ipython notebook","is_about":true,"sentiment_score":0.0,"strength_score":1.0,"sentiment_polarity":"neutral"}],"phrases":[{"title":"IPython notebooks now render","sentiment_polarity":"neutral","type":"possible"}],"summary":"Jupyter/IPython notebooks now render on GitHub... Learn more: https://t.co/LvEHeykDDp... ","config_id":"1d9a3af7-825a-4a64-92fa-f05fa11ba5c7","source_text":"Jupyter/IPython notebooks now render on GitHub. Learn more: https://t.co/LvEHeykDDp","language_score":5.0,"sentiment_score":0.0,"sentiment_polarity":"neutral","language":"English","id":"9850050039"},{"status":"PROCESSED","config_id":"1d9a3af7-825a-4a64-92fa-f05fa11ba5c7","source_text":"LALALALALALA","language_score":1.0e-07,"sentiment_score":0.0,"sentiment_polarity":"neutral","language":"Unknown","id":"8910542924"},{"status":"PROCESSED","themes":[{"title":"positive tweet","stemmed":"positive tweet","evidence":4,"normalized":"positive tweet","is_about":true,"sentiment_score":0.6,"strength_score":1.0,"sentiment_polarity":"positive"},{"title":"passed Semantria","stemmed":"passed semantria","evidence":4,"normalized":"passed semantria","is_about":true,"sentiment_score":0.3,"strength_score":1.0,"sentiment_polarity":"neutral"}],"phrases":[{"title":"Awesome","sentiment_score":1.2,"sentiment_polarity":"positive","is_negated":false,"is_intensified":false,"type":"detected"},{"title":"positive tweet","sentiment_polarity":"neutral","type":"possible"}],"summary":"This positive tweet passed Semantria... ","config_id":"1d9a3af7-825a-4a64-92fa-f05fa11ba5c7","source_text":"This positive tweet passed Semantria. Awesome!","language_score":2.0,"sentiment_score":1.2,"sentiment_polarity":"positive","topics":[{"hitcount":0,"title":"Social Media","sentiment_score":0.0,"strength_score":0.49724224,"sentiment_polarity":"neutral","type":"concept"}],"language":"English","id":"0968541673"},{"status":"PROCESSED","themes":[{"title":"awesome tweet","stemmed":"awesome tweet","evidence":4,"normalized":"awesome tweet","is_about":true,"sentiment_score":0.6,"strength_score":1.0,"sentiment_polarity":"positive"},{"title":"Rails course","stemmed":"rails course","evidence":4,"normalized":"rails course","is_about":true,"sentiment_score":0.6,"strength_score":1.0,"sentiment_polarity":"positive"}],"phrases":[{"title":"awesome","sentiment_score":0.6,"sentiment_polarity":"positive","is_negated":false,"is_intensified":false,"type":"detected"}],"summary":"Another awesome tweet from the Rails course... ","config_id":"1d9a3af7-825a-4a64-92fa-f05fa11ba5c7","source_text":"Another awesome tweet from the Rails course","language_score":4.0,"sentiment_score":0.6,"sentiment_polarity":"positive","topics":[{"hitcount":0,"title":"Sports","sentiment_score":0.6,"strength_score":0.48069572,"sentiment_polarity":"positive","type":"concept"}],"language":"English","id":"6169761398"},{"status":"PROCESSED","phrases":[{"title":"awesome","sentiment_score":0.6,"sentiment_polarity":"positive","is_negated":false,"is_intensified":false,"type":"detected"}],"config_id":"1d9a3af7-825a-4a64-92fa-f05fa11ba5c7","source_text":"This is awesome","language_score":3.0,"sentiment_score":0.6,"sentiment_polarity":"positive","language":"English","id":"0006719861"},{"entities":[{"evidence":0,"title":"https://t.co/oeNcoaaM3J","is_about":false,"confident":true,"entity_type":"Regex","sentiment_score":0.0,"sentiment_polarity":"neutral","label":"url","type":"named"}],"status":"PROCESSED","phrases":[{"title":"Tricks","sentiment_score":-0.46,"sentiment_polarity":"negative","is_negated":false,"is_intensified":false,"type":"detected"}],"summary":"I'll be giving a talk about React Tips \u0026amp; Tricks - https://t.co/oeNcoaaM3J... ","config_id":"1d9a3af7-825a-4a64-92fa-f05fa11ba5c7","source_text":"I'll be giving a talk about React Tips \u0026amp; Tricks - https://t.co/oeNcoaaM3J","language_score":7.0,"sentiment_score":-0.46,"sentiment_polarity":"negative","language":"English","id":"9152529597"},{"entities":[{"evidence":6,"title":" @AtomEditor","is_about":true,"confident":true,"entity_type":"Person","sentiment_score":0.5,"sentiment_polarity":"neutral","label":"Twitterer","type":"named"},{"evidence":0,"title":"https://t.co/o4eo3Semb8","is_about":false,"confident":true,"entity_type":"Regex","sentiment_score":0.0,"sentiment_polarity":"neutral","label":"url","type":"named"}],"status":"PROCESSED","phrases":[{"title":"Happy","sentiment_score":0.5,"sentiment_polarity":"positive","is_negated":false,"is_intensified":false,"type":"detected"}],"summary":"Happy 1 Year Open Source to  @AtomEditor... See how far they've come and where they're headed: https://t.co/o4eo3Semb8... ","config_id":"1d9a3af7-825a-4a64-92fa-f05fa11ba5c7","source_text":"Happy 1 Year Open Source to @AtomEditor. See how far they've come and where they're headed: https://t.co/o4eo3Semb8","language_score":14.0,"sentiment_score":0.5,"sentiment_polarity":"positive","language":"English","id":"5196164515"},{"status":"FAILED","summary":"Failed to parse document","config_id":"1d9a3af7-825a-4a64-92fa-f05fa11ba5c7","sentiment_score":0.0,"sentiment_polarity":"neutral","id":"6348181622"},{"entities":[{"evidence":0,"title":"https://t.co/Qq2YEpdiQJ","is_about":false,"confident":true,"entity_type":"Regex","sentiment_score":0.0,"sentiment_polarity":"neutral","label":"url","type":"named"}],"status":"PROCESSED","summary":"List your project's releases on your GitHub Pages site https://t.co/Qq2YEpdiQJ... ","config_id":"1d9a3af7-825a-4a64-92fa-f05fa11ba5c7","source_text":"List your project's releases on your GitHub Pages site https://t.co/Qq2YEpdiQJ","language_score":9.0,"sentiment_score":0.0,"sentiment_polarity":"neutral","language":"English","id":"1293971138"}]